cmsplugin_form_handler/__init__.py
cmsplugin_form_handler/cms_plugins.py
cmsplugin_form_handler/forms.py
cmsplugin_form_handler/urls.py
cmsplugin_form_handler/views.py
cmsplugin_form_handler/templatetags/__init__.py
cmsplugin_form_handler/templatetags/cmsplugin_form_tags.py
cmsplugin_form_handler-0.2.0.dist-info/DESCRIPTION.rst
cmsplugin_form_handler-0.2.0.dist-info/METADATA
cmsplugin_form_handler-0.2.0.dist-info/RECORD
cmsplugin_form_handler-0.2.0.dist-info/WHEEL
cmsplugin_form_handler-0.2.0.dist-info/metadata.json
cmsplugin_form_handler-0.2.0.dist-info/top_level.txt
test_project/__init__.py
test_project/settings.py
test_project/urls.py
test_project/wsgi.py
test_project/apps/__init__.py
test_project/apps/sample/__init__.py
test_project/apps/sample/admin.py
test_project/apps/sample/cms_plugins.py
test_project/apps/sample/forms.py
test_project/apps/sample/models.py
test_project/apps/sample/migrations/0001_initial.py
test_project/apps/sample/migrations/0002_samplepluginmodel.py
test_project/apps/sample/migrations/__init__.py
tests/__init__.py
tests/base.py
tests/test_plugins.py
